MANIFEST.in
board_warehouse_view.xml
partner_view.xml
product_data.xml
product_view.xml
res_config_view.xml
setup.py
stock_data.xml
stock_demo.xml
stock_demo.yml
stock_incoterms.xml
stock_report.xml
stock_sequence.xml
stock_view.xml
stock_workflow.xml
./__init__.py
./__openerp__.py
./partner.py
./product.py
./res_config.py
./stock.py
./report/__init__.py
./report/lot_overview.py
./report/lot_overview_all.py
./report/picking.py
./report/product_stock.py
./report/report_stock.py
./report/report_stock_move.py
./report/stock_by_location.py
./report/stock_graph.py
./report/stock_inventory_move_report.py
./tests/__init__.py
./tests/test_multicompany.py
./wizard/__init__.py
./wizard/stock_change_product_qty.py
./wizard/stock_change_standard_price.py
./wizard/stock_fill_inventory.py
./wizard/stock_inventory_line_split.py
./wizard/stock_inventory_merge.py
./wizard/stock_invoice_onshipping.py
./wizard/stock_location_product.py
./wizard/stock_move.py
./wizard/stock_partial_move.py
./wizard/stock_partial_picking.py
./wizard/stock_return_picking.py
./wizard/stock_splitinto.py
./wizard/stock_traceability.py
i18n/ar.po
i18n/bg.po
i18n/bs.po
i18n/ca.po
i18n/cs.po
i18n/da.po
i18n/de.po
i18n/el.po
i18n/es.po
i18n/es_AR.po
i18n/es_BO.po
i18n/es_CL.po
i18n/es_CR.po
i18n/es_DO.po
i18n/es_EC.po
i18n/es_MX.po
i18n/es_PE.po
i18n/es_VE.po
i18n/et.po
i18n/fi.po
i18n/fr.po
i18n/gl.po
i18n/hr.po
i18n/hu.po
i18n/id.po
i18n/it.po
i18n/ja.po
i18n/ko.po
i18n/lt.po
i18n/lv.po
i18n/mk.po
i18n/mn.po
i18n/nb.po
i18n/nl.po
i18n/nl_BE.po
i18n/pl.po
i18n/pt.po
i18n/pt_BR.po
i18n/ro.po
i18n/ru.po
i18n/sl.po
i18n/sq.po
i18n/sr.po
i18n/sr@latin.po
i18n/stock.pot
i18n/sv.po
i18n/th.po
i18n/th_TH.po
i18n/tlh.po
i18n/tr.po
i18n/uk.po
i18n/vi.po
i18n/zh_CN.po
i18n/zh_TW.po
images/delivery_orders.jpeg
images/inventory_analysis.jpeg
images/location.jpeg
images/moves_analysis.jpeg
images/physical_inventories.jpeg
images/stock_forecast_report.png
images/warehouse-hover.png
images/warehouse.png
openerp_stock.egg-info/PKG-INFO
openerp_stock.egg-info/SOURCES.txt
openerp_stock.egg-info/dependency_links.txt
openerp_stock.egg-info/requires.txt
openerp_stock.egg-info/top_level.txt
